ai_tqa/__init__.py
ai_tqa/model.py
ai_tqa/data/data.json
ai_tqa/data/my_model.h5
ai_tqa-1.1.4.dist-info/METADATA
ai_tqa-1.1.4.dist-info/WHEEL
ai_tqa-1.1.4.dist-info/entry_points.txt
ai_tqa-1.1.4.dist-info/top_level.txt
ai_tqa-1.1.4.dist-info/RECORD
