Metadata-Version: 2.1
Name: ai-tqa
Version: 1.1.4
Summary: A text evaluation module using AI-TQA1 Basic
Home-page: https://github.com/krozen-dev/AI_TextScan
Author: _KroZen_
Author-email: your.email@example.com
Classifier: Programming Language :: Python :: 3
Classifier: License :: OSI Approved :: MIT License
Classifier: Operating System :: OS Independent
Requires-Python: >=3.8
Requires-Dist: tensorflow
Requires-Dist: nltk
Requires-Dist: requests
